{
    "/js/manifest.js": "/js/manifest.js?id=7db827d654313dce4250",
    "/js/vendor.js": "/js/vendor.js?id=1c280705305bd7ecc587",
    "/js/app.js": "/js/app.js?id=65fc7f177993bfc0bed4",
    "/css/app-ltr.css": "/css/app-ltr.css?id=77f704d7e4ff43d85da0",
    "/css/app-rtl.css": "/css/app-rtl.css?id=8be701180e9c5c53d2e4",
    "/css/stripe.css": "/css/stripe.css?id=76c70a7b11ae5f38a725",
    "/js/stripe.js": "/js/stripe.js?id=02a4aecbbf654979c44c",
    "/js/u2f-api.js": "/js/u2f-api.js?id=1948d3efdfd801bed14a"
}
